{"kanjiInfos": [{"meanings": ["melodious", "clear", "bright", "serene", "cheerful"], "onyomi": [" \u30ed\u30a6"], "kanji": "\u6717", "kunyomi": [" \u307b\u304c.\u3089\u304b", "\u3042\u304d.\u3089\u304b"], "radicals": ["\u6708", "\u826e"]}, {"meanings": ["stomach", "paunch", "crop", "craw"], "onyomi": [" \u30a4"], "kanji": "\u80c3", "kunyomi": [], "radicals": ["\u6708", "\u7530"]}, {"meanings": ["freshwater trout", "smelt"], "onyomi": [" \u30c7\u30f3", "\u30cd\u30f3"], "kanji": "\u9b8e", "kunyomi": [" \u3042\u3086", "\u306a\u307e\u305a"], "radicals": ["\u9b5a", "\u53e3", "\u7530", "\u535c"]}, {"meanings": ["apricot"], "onyomi": [" \u30ad\u30e7\u30a6", "\u30a2\u30f3", "\u30b3\u30a6"], "kanji": "\u674f", "kunyomi": [" \u3042\u3093\u305a"], "radicals": ["\u53e3", "\u6728"]}, {"meanings": ["root", "radical", "head (pimple)"], "onyomi": [" \u30b3\u30f3"], "kanji": "\u6839", "kunyomi": [" \u306d", "-\u306d"], "radicals": ["\u826e", "\u6728"]}]}