{"kanjiInfos": [{"meanings": ["time", "about", "toward"], "onyomi": [" \u30b1\u30a4", "\u30ad\u30e7\u30a6"], "kanji": "\u9803", "kunyomi": [" \u3053\u308d", "\u3054\u308d", "\u3057\u3070\u3089.\u304f"], "radicals": ["\u8c9d", "\u76ee", "\u30cf", "\u9801", "\u5315"]}, {"meanings": ["one (in documents)"], "onyomi": [" \u30a4\u30c1", "\u30a4\u30c4"], "kanji": "\u58f1", "kunyomi": [" \u3072\u3068\u3064"], "radicals": ["\u58eb", "\u5196", "\u5315"]}, {"meanings": ["shellfish"], "onyomi": [" \u30d0\u30a4"], "kanji": "\u8c9d", "kunyomi": [" \u304b\u3044"], "radicals": ["\u76ee", "\u30cf"]}, {"meanings": ["eight", "eight radical (no. 12)"], "onyomi": [" \u30cf\u30c1"], "kanji": "\u516b", "kunyomi": [" \u3084", "\u3084.\u3064", "\u3084\u3063.\u3064", "\u3088\u3046"], "radicals": ["\u30cf"]}, {"meanings": ["truth", "reality", "Buddhist sect"], "onyomi": [" \u30b7\u30f3"], "kanji": "\u771e", "kunyomi": [" \u307e", "\u307e\u3053\u3068"], "radicals": ["\u30cf", "\u76ee", "\u5315"]}]}