{"kanjiInfos": [{"meanings": ["fear", "uneasiness", "anxiety", "concern", "expectation", "consideration"], "onyomi": [" \u30b0"], "kanji": "\u865e", "kunyomi": [" \u304a\u305d\u308c", "\u304a\u3082\u3093\u3071\u304b.\u308b", "\u306f\u304b.\u308b", "\u3046\u308c.\u3048\u308b", "\u3042\u3056\u3080.\u304f", "\u3042\u3084\u307e.\u308b", "\u306e\u305e.\u3080", "\u305f\u306e.\u3057\u3080"], "radicals": ["\u53e3", "\u30cf", "\u535c", "\u5315", "\u5382", "\u864d"]}, {"meanings": ["pressure", "push", "overwhelm", "oppress", "dominate"], "onyomi": [" \u30a2\u30c4", "\u30a8\u30f3", "\u30aa\u30a6"], "kanji": "\u5727", "kunyomi": [" \u304a.\u3059", "\u3078.\u3059", "\u304a\u3055.\u3048\u308b", "\u304a.\u3055\u3048\u308b"], "radicals": ["\u571f", "\u5382"]}, {"meanings": ["lie", "falsehood"], "onyomi": [" \u30ad\u30e7", "\u30b3"], "kanji": "\u5618", "kunyomi": [" \u3046\u305d", "\u3075.\u304f"], "radicals": ["\u53e3", "\u535c", "\u5315", "\u5382", "\u864d"]}, {"meanings": ["square jewel", "corner", "angle", "edge"], "onyomi": [" \u30b1\u30a4", "\u30b1"], "kanji": "\u572d", "kunyomi": [], "radicals": ["\u571f"]}, {"meanings": ["give", "do something for", "kingdom of Wu"], "onyomi": [" \u30b4"], "kanji": "\u5449", "kunyomi": [" \u304f.\u308c\u308b", "\u304f\u308c"], "radicals": ["\u53e3", "\u30cf"]}]}