{"kanjiInfos": [{"meanings": ["grains", "drop", "counter for tiny particles"], "onyomi": [" \u30ea\u30e5\u30a6"], "kanji": "\u7c92", "kunyomi": [" \u3064\u3076"], "radicals": ["\u7c73", "\u7acb"]}, {"meanings": ["catalpa tree", "woodblock printing"], "onyomi": [" \u30b7"], "kanji": "\u6893", "kunyomi": [" \u3042\u305a\u3055"], "radicals": ["\u5341", "\u8f9b", "\u6728", "\u7acb"]}, {"meanings": ["millet"], "onyomi": [" \u30be\u30af", "\u30b7\u30e7\u30af", "\u30bd\u30af"], "kanji": "\u7c9f", "kunyomi": [" \u3042\u308f", "\u3082\u307f"], "radicals": ["\u897f", "\u7c73"]}, {"meanings": ["madder", "red dye", "Turkey red"], "onyomi": [" \u30bb\u30f3"], "kanji": "\u831c", "kunyomi": [" \u3042\u304b\u306d"], "radicals": ["\u897f", "\u2ebe"]}, {"meanings": ["chestnut"], "onyomi": [" \u30ea\u30c4", "\u30ea"], "kanji": "\u6817", "kunyomi": [" \u304f\u308a", "\u304a\u306e\u306e\u304f"], "radicals": ["\u897f", "\u6728"]}]}