{"kanjiInfos": [{"meanings": ["courts", "imperial court", "government office"], "onyomi": [" \u30c6\u30a4"], "kanji": "\u5ef7", "kunyomi": [], "radicals": ["\u738b", "\u5ef4", "\u58eb"]}, {"meanings": ["one (in documents)"], "onyomi": [" \u30a4\u30c1", "\u30a4\u30c4"], "kanji": "\u58f1", "kunyomi": [" \u3072\u3068\u3064"], "radicals": ["\u58eb", "\u5196", "\u5315"]}, {"meanings": ["carry", "luck", "destiny", "fate", "lot", "transport", "progress", "advance"], "onyomi": [" \u30a6\u30f3"], "kanji": "\u904b", "kunyomi": [" \u306f\u3053.\u3076"], "radicals": ["\ufa66", "\u8eca", "\u5196"]}, {"meanings": ["army", "force", "troops", "war", "battle"], "onyomi": [" \u30b0\u30f3"], "kanji": "\u8ecd", "kunyomi": [" \u3044\u304f\u3055"], "radicals": ["\u8eca", "\u5196"]}, {"meanings": ["roar", "thunder", "boom resound"], "onyomi": [" \u30b4\u30a6", "\u30b3\u30a6"], "kanji": "\u8f5f", "kunyomi": [" \u3068\u3069\u308d.\u304b\u3059", "\u3068\u3069\u308d.\u304f"], "radicals": ["\u8eca"]}]}