{"uuid": "eb361e73-1391-4206-825c-e909d0937663", "kanjiInfos": [{"meanings": ["outside"], "onyomi": [" \u30ac\u30a4", "\u30b2"], "kanji": "\u5916", "kunyomi": [" \u305d\u3068", "\u307b\u304b", "\u306f\u305a.\u3059", "\u306f\u305a.\u308c\u308b", "\u3068-"], "radicals": ["\u5915", "\u535c"]}, {"meanings": ["many", "frequent", "much"], "onyomi": [" \u30bf"], "kanji": "\u591a", "kunyomi": [" \u304a\u304a.\u3044", "\u307e\u3055.\u306b", "\u307e\u3055.\u308b"], "radicals": ["\u5915", "\u5915"]}, {"meanings": ["store", "shop"], "onyomi": [" \u30c6\u30f3"], "kanji": "\u5e97", "kunyomi": [" \u307f\u305b", "\u305f\u306a"], "radicals": ["\u5e7f", "\u535c", "\u53e3"]}, {"meanings": ["name", "noted", "distinguished", "reputation"], "onyomi": [" \u30e1\u30a4", "\u30df\u30e7\u30a6"], "kanji": "\u540d", "kunyomi": [" \u306a", "-\u306a"], "radicals": ["\u5915", "\u53e3"]}, {"meanings": ["word", "speech", "language"], "onyomi": [" \u30b4"], "kanji": "\u8a9e", "kunyomi": [" \u304b\u305f.\u308b", "\u304b\u305f.\u3089\u3046"], "radicals": ["\u8a00", "\u4e94", "\u53e3"]}]}