{"uuid": "2918ea41-dd0d-4259-bf58-e048c97e2e9a", "kanjiInfos": [{"meanings": ["what"], "onyomi": [" \u30ab"], "kanji": "\u4f55", "kunyomi": [" \u306a\u306b", "\u306a\u3093", "\u306a\u306b-", "\u306a\u3093-"], "radicals": ["\u2e85", "\u53e3", "\u4e85"]}, {"meanings": ["flower"], "onyomi": [" \u30ab", "\u30b1"], "kanji": "\u82b1", "kunyomi": [" \u306f\u306a"], "radicals": ["\u2e85", "\u5315", "\u2ebe"]}, {"meanings": ["rest", "day off", "retire", "sleep"], "onyomi": [" \u30ad\u30e5\u30a6"], "kanji": "\u4f11", "kunyomi": [" \u3084\u3059.\u3080", "\u3084\u3059.\u307e\u308b", "\u3084\u3059.\u3081\u308b"], "radicals": ["\u2e85", "\u6728"]}, {"meanings": ["old"], "onyomi": [" \u30b3"], "kanji": "\u53e4", "kunyomi": [" \u3075\u308b.\u3044", "\u3075\u308b-", "-\u3075\u308b.\u3059"], "radicals": ["\u53e3", "\u5341"]}, {"meanings": ["leg", "foot", "be sufficient", "counter for pairs of footwear"], "onyomi": [" \u30bd\u30af"], "kanji": "\u8db3", "kunyomi": [" \u3042\u3057", "\u305f.\u308a\u308b", "\u305f.\u308b", "\u305f.\u3059"], "radicals": ["\u53e3"]}]}