{"uuid": "64a89974-62b1-44b5-b361-1267d55590fa", "kanjiInfos": [{"meanings": ["below", "down", "descend", "give", "low", "inferior"], "onyomi": [" \u30ab", "\u30b2"], "kanji": "\u4e0b", "kunyomi": [" \u3057\u305f", "\u3057\u3082", "\u3082\u3068", "\u3055.\u3052\u308b", "\u3055.\u304c\u308b", "\u304f\u3060.\u308b", "\u304f\u3060.\u308a", "\u304f\u3060.\u3059", "-\u304f\u3060.\u3059", "\u304f\u3060.\u3055\u308b", "\u304a.\u308d\u3059", "\u304a.\u308a\u308b"], "radicals": ["\uff5c", "\u4e00", "\u535c"]}, {"meanings": ["outside"], "onyomi": [" \u30ac\u30a4", "\u30b2"], "kanji": "\u5916", "kunyomi": [" \u305d\u3068", "\u307b\u304b", "\u306f\u305a.\u3059", "\u306f\u305a.\u308c\u308b", "\u3068-"], "radicals": ["\u535c", "\u5915"]}, {"meanings": ["word", "speech", "language"], "onyomi": [" \u30b4"], "kanji": "\u8a9e", "kunyomi": [" \u304b\u305f.\u308b", "\u304b\u305f.\u3089\u3046"], "radicals": ["\u4e00", "\u8a00", "\u53e3", "\u4e94"]}, {"meanings": ["leg", "foot", "be sufficient", "counter for pairs of footwear"], "onyomi": [" \u30bd\u30af"], "kanji": "\u8db3", "kunyomi": [" \u3042\u3057", "\u305f.\u308a\u308b", "\u305f.\u308b", "\u305f.\u3059"], "radicals": ["\u53e3"]}, {"meanings": ["many", "frequent", "much"], "onyomi": [" \u30bf"], "kanji": "\u591a", "kunyomi": [" \u304a\u304a.\u3044", "\u307e\u3055.\u306b", "\u307e\u3055.\u308b"], "radicals": ["\u5915"]}]}