{"uuid": "821d8daf-bbb9-4795-a24f-83eeebc8590e", "kanjiInfos": [{"meanings": ["severance", "decline", "refuse", "apologize", "warn", "dismiss", "prohibit", "decision", "judgement", "cutting"], "onyomi": [" \u30c0\u30f3"], "kanji": "\u65ad", "kunyomi": [" \u305f.\u3064", "\u3053\u3068\u308f.\u308b", "\u3055\u3060.\u3081\u308b"], "radicals": ["\u7c73", "\uff5c", "\u4e00", "\u65a4"]}, {"meanings": ["ill", "sick"], "onyomi": [" \u30d3\u30e7\u30a6", "\u30d8\u30a4"], "kanji": "\u75c5", "kunyomi": [" \u3084.\u3080", "-\u3084.\u307f", "\u3084\u307e\u3044"], "radicals": ["\u7592", "\u4e00", "\u4eba", "\u5182"]}, {"meanings": ["come", "due", "next", "cause", "become"], "onyomi": [" \u30e9\u30a4", "\u30bf\u30a4"], "kanji": "\u6765", "kunyomi": [" \u304f.\u308b", "\u304d\u305f.\u308b", "\u304d\u305f.\u3059", "\u304d.\u305f\u3059", "\u304d.\u305f\u308b", "\u304d", "\u3053"], "radicals": ["\u4e00", "\u7c73"]}, {"meanings": ["large", "big"], "onyomi": [" \u30c0\u30a4", "\u30bf\u30a4"], "kanji": "\u5927", "kunyomi": [" \u304a\u304a-", "\u304a\u304a.\u304d\u3044", "-\u304a\u304a.\u3044\u306b"], "radicals": ["\u4e00", "\u4eba"]}, {"meanings": ["ten"], "onyomi": [" \u30b8\u30e5\u30a6", "\u30b8\u30c3", "\u30b8\u30e5\u30c3"], "kanji": "\u5341", "kunyomi": [" \u3068\u304a", "\u3068", "\u305d"], "radicals": ["\u4e00", "\uff5c"]}]}