{"uuid": "afdf5fa7-9705-4142-8d26-25ebef12868c", "kanjiInfos": [{"meanings": ["utilize", "business", "service", "use", "employ"], "onyomi": [" \u30e8\u30a6"], "kanji": "\u7528", "kunyomi": [" \u3082\u3061.\u3044\u308b"], "radicals": ["\u5182", "\u4e8c", "\uff5c"]}, {"meanings": ["five"], "onyomi": [" \u30b4"], "kanji": "\u4e94", "kunyomi": [" \u3044\u3064", "\u3044\u3064.\u3064"], "radicals": ["\u4e00", "\uff5c", "\u30e6"]}, {"meanings": ["left"], "onyomi": [" \u30b5", "\u30b7\u30e3"], "kanji": "\u5de6", "kunyomi": [" \u3072\u3060\u308a"], "radicals": ["\u4e00", "\u30ce", "\u5de5"]}, {"meanings": ["month", "moon"], "onyomi": [" \u30b2\u30c4", "\u30ac\u30c4"], "kanji": "\u6708", "kunyomi": [" \u3064\u304d"], "radicals": ["\u5182", "\u4e8c"]}, {"meanings": ["ten"], "onyomi": [" \u30b8\u30e5\u30a6", "\u30b8\u30c3", "\u30b8\u30e5\u30c3"], "kanji": "\u5341", "kunyomi": [" \u3068\u304a", "\u3068", "\u305d"], "radicals": ["\u4e00", "\uff5c"]}]}