{"uuid": "3d03f230-08db-4cea-90f1-6f5f0822a7b6", "kanjiInfos": [{"meanings": ["few", "little"], "onyomi": [" \u30b7\u30e7\u30a6"], "kanji": "\u5c11", "kunyomi": [" \u3059\u304f.\u306a\u3044", "\u3059\u3053.\u3057"], "radicals": ["\u5c0f", "\u30ce"]}, {"meanings": ["spirit", "mind", "air", "atmosphere", "mood"], "onyomi": [" \u30ad", "\u30b1"], "kanji": "\u6c17", "kunyomi": [" \u304d"], "radicals": ["\u6c14", "\u4e36", "\u30ce"]}, {"meanings": ["country"], "onyomi": [" \u30b3\u30af"], "kanji": "\u56fd", "kunyomi": [" \u304f\u306b"], "radicals": ["\u53e3", "\u738b", "\u4e36"]}, {"meanings": ["person"], "onyomi": [" \u30b8\u30f3", "\u30cb\u30f3"], "kanji": "\u4eba", "kunyomi": [" \u3072\u3068", "-\u308a", "-\u3068"], "radicals": ["\u30ce", "\u4e36"]}, {"meanings": ["thousand"], "onyomi": [" \u30bb\u30f3"], "kanji": "\u5343", "kunyomi": [" \u3061"], "radicals": ["\u30ce", "\u5341"]}]}