{"uuid": "3e4554b1-b164-4a1e-b4c2-b31fae744bc8", "kanjiInfos": [{"meanings": ["cut", "cutoff", "be sharp"], "onyomi": [" \u30bb\u30c4", "\u30b5\u30a4"], "kanji": "\u5207", "kunyomi": [" \u304d.\u308b", "-\u304d.\u308b", "\u304d.\u308a", "-\u304d.\u308a", "-\u304e.\u308a", "\u304d.\u308c\u308b", "-\u304d.\u308c\u308b", "\u304d.\u308c", "-\u304d.\u308c", "-\u304e.\u308c"], "radicals": ["\u5315", "\u5200"]}, {"meanings": ["flower"], "onyomi": [" \u30ab", "\u30b1"], "kanji": "\u82b1", "kunyomi": [" \u306f\u306a"], "radicals": ["\u2ebe", "\u2e85", "\u5315"]}, {"meanings": ["part", "minute of time", "segment", "share", "degree", "one's lot", "duty", "understand", "know", "rate", "1%", "chances", "shaku", "100"], "onyomi": [" \u30d6\u30f3", "\u30d5\u30f3", "\u30d6"], "kanji": "\u5206", "kunyomi": [" \u308f.\u3051\u308b", "\u308f.\u3051", "\u308f.\u304b\u308c\u308b", "\u308f.\u304b\u308b", "\u308f.\u304b\u3064"], "radicals": ["\u30cf", "\u5200"]}, {"meanings": ["north"], "onyomi": [" \u30db\u30af"], "kanji": "\u5317", "kunyomi": [" \u304d\u305f"], "radicals": ["\u723f", "\u5315"]}, {"meanings": ["tree", "wood"], "onyomi": [" \u30dc\u30af", "\u30e2\u30af"], "kanji": "\u6728", "kunyomi": [" \u304d", "\u3053-"], "radicals": ["\u5341", "\u30cf"]}]}